flask_otp.py
flask_otp-1.2.dist-info/DESCRIPTION.rst
flask_otp-1.2.dist-info/METADATA
flask_otp-1.2.dist-info/RECORD
flask_otp-1.2.dist-info/WHEEL
flask_otp-1.2.dist-info/metadata.json
flask_otp-1.2.dist-info/top_level.txt
