Metadata-Version: 2.0
Name: flask-otp
Version: 1.2
Summary: One-Time Password extension to Flask
Home-page: https://github.com/linw1995/flask-otp
Author: linw
Author-email: linw1995@icloud.com
License: MIT
Platform: any
Classifier: Environment :: Web Environment
Classifier: Intended Audience :: Developers
Classifier: License :: OSI Approved :: MIT License
Classifier: Operating System :: OS Independent
Classifier: Programming Language :: Python
Classifier: Programming Language :: Python :: 2.7
Classifier: Programming Language :: Python :: 3.6
Classifier: Topic :: Internet :: WWW/HTTP :: Dynamic Content
Classifier: Topic :: Software Development :: Libraries :: Python Modules
Requires-Dist: Flask
Requires-Dist: pyotp
Requires-Dist: qrcode
Requires-Dist: six
